modelator_py/__init__.py
modelator_py/apalache/__init__.py
modelator_py/apalache/apalache_help_0.23.0.txt
modelator_py/apalache/args.py
modelator_py/apalache/cli.py
modelator_py/apalache/pure.py
modelator_py/apalache/raw.py
modelator_py/cli.py
modelator_py/helper.py
modelator_py/tlc/__init__.py
modelator_py/tlc/args.py
modelator_py/tlc/cli.py
modelator_py/tlc/pure.py
modelator_py/tlc/raw.py
modelator_py/tlc/tlc_help_2.18.txt
modelator_py/util/__init__.py
modelator_py/util/cli.py
modelator_py/util/informal_trace_format.py
modelator_py/util/tla/LICENSE
modelator_py/util/tla/README.md
modelator_py/util/tla/README_license.md
modelator_py/util/tla/__init__.py
modelator_py/util/tla/_combinators.py
modelator_py/util/tla/_error.py
modelator_py/util/tla/_expr_parser.py
modelator_py/util/tla/_intf.py
modelator_py/util/tla/_location.py
modelator_py/util/tla/_module_parser.py
modelator_py/util/tla/_optable.py
modelator_py/util/tla/_proof_parser.py
modelator_py/util/tla/_tla_combinators.py
modelator_py/util/tla/ast.py
modelator_py/util/tla/examples/Counter.tla
modelator_py/util/tla/examples/README.md
modelator_py/util/tla/examples/__init__.py
modelator_py/util/tla/examples/parsing_tla_expressions.py
modelator_py/util/tla/examples/parsing_tla_modules.py
modelator_py/util/tla/examples/syntax_tree_visitor.py
modelator_py/util/tla/iter.py
modelator_py/util/tla/lex.py
modelator_py/util/tla/parser.py
modelator_py/util/tla/to_str.py
modelator_py/util/tla/tokens.py
modelator_py/util/tla/visit.py
modelator_py/util/tlc/__init__.py
modelator_py/util/tlc/cli.py
modelator_py/util/tlc/itf.py
modelator_py/util/tlc/state_to_informal_trace_format.py
modelator_py/util/tlc/stdout_to_informal_trace_format.py
modelator_py-0.2.6.dist-info/entry_points.txt
modelator_py-0.2.6.dist-info/LICENSE
modelator_py-0.2.6.dist-info/WHEEL
modelator_py-0.2.6.dist-info/METADATA
modelator_py-0.2.6.dist-info/RECORD
