Metadata-Version: 2.1
Name: modelator-py
Version: 0.2.6
Summary: Lightweight utilities to assist model writing and model-based testing activities using the TLA+ ecosystem
Home-page: https://mbt.informal.systems/
Keywords: utility,tla,tlaplus,tlc,apalache
Author: Daniel Tisdall
Author-email: daniel@informal.systems
Requires-Python: >=3.8,<4.0
Classifier: Programming Language :: Python :: 3
Classifier: Programming Language :: Python :: 3.8
Classifier: Programming Language :: Python :: 3.9
Classifier: Programming Language :: Python :: 3.10
Classifier: Programming Language :: Python :: 3.11
Requires-Dist: fire (>=0.4,<0.5)
Requires-Dist: infix (>=1.2,<2.0)
Requires-Dist: pathos (>=0.3,<0.4)
Requires-Dist: ply (>=3.11,<4.0)
Project-URL: Documentation, https://github.com/informalsystems/modelator-py/
Project-URL: Repository, https://github.com/informalsystems/modelator-py/
